[
  {
    "type": "action",
    "named": true,
    "fields": {},
    "children": {
      "multiple": true,
      "required": true,
      "types": [
        {
          "type": "prop",
          "named": true
        }
      ]
    }
  },
  {
    "type": "and",
    "named": true,
    "fields": {},
    "children": {
      "multiple": true,
      "required": true,
      "types": [
        {
          "type": "formula",
          "named": true
        }
      ]
    }
  },
  {
    "type": "boolean",
    "named": true,
    "fields": {}
  },
  {
    "type": "box",
    "named": true,
    "fields": {},
    "children": {
      "multiple": true,
      "required": true,
      "types": [
        {
          "type": "action",
          "named": true
        },
        {
          "type": "formula",
          "named": true
        }
      ]
    }
  },
  {
    "type": "dia",
    "named": true,
    "fields": {},
    "children": {
      "multiple": true,
      "required": true,
      "types": [
        {
          "type": "action",
          "named": true
        },
        {
          "type": "formula",
          "named": true
        }
      ]
    }
  },
  {
    "type": "empty_box",
    "named": true,
    "fields": {},
    "children": {
      "multiple": false,
      "required": true,
      "types": [
        {
          "type": "formula",
          "named": true
        }
      ]
    }
  },
  {
    "type": "empty_dia",
    "named": true,
    "fields": {},
    "children": {
      "multiple": false,
      "required": true,
      "types": [
        {
          "type": "formula",
          "named": true
        }
      ]
    }
  },
  {
    "type": "formula",
    "named": true,
    "fields": {},
    "children": {
      "multiple": false,
      "required": true,
      "types": [
        {
          "type": "and",
          "named": true
        },
        {
          "type": "boolean",
          "named": true
        },
        {
          "type": "box",
          "named": true
        },
        {
          "type": "dia",
          "named": true
        },
        {
          "type": "empty_box",
          "named": true
        },
        {
          "type": "empty_dia",
          "named": true
        },
        {
          "type": "or",
          "named": true
        },
        {
          "type": "prop",
          "named": true
        },
        {
          "type": "state_set_variable",
          "named": true
        }
      ]
    }
  },
  {
    "type": "or",
    "named": true,
    "fields": {},
    "children": {
      "multiple": true,
      "required": true,
      "types": [
        {
          "type": "formula",
          "named": true
        }
      ]
    }
  },
  {
    "type": "prop",
    "named": true,
    "fields": {},
    "children": {
      "multiple": true,
      "required": true,
      "types": [
        {
          "type": "prop_label",
          "named": true
        },
        {
          "type": "sign",
          "named": true
        }
      ]
    }
  },
  {
    "type": "prop_label",
    "named": true,
    "fields": {}
  },
  {
    "type": "sign",
    "named": true,
    "fields": {}
  },
  {
    "type": "source_file",
    "named": true,
    "fields": {},
    "children": {
      "multiple": false,
      "required": true,
      "types": [
        {
          "type": "formula",
          "named": true
        }
      ]
    }
  },
  {
    "type": "(",
    "named": false
  },
  {
    "type": ")",
    "named": false
  },
  {
    "type": "+",
    "named": false
  },
  {
    "type": ",",
    "named": false
  },
  {
    "type": "-",
    "named": false
  },
  {
    "type": "<",
    "named": false
  },
  {
    "type": ">",
    "named": false
  },
  {
    "type": "?",
    "named": false
  },
  {
    "type": "[",
    "named": false
  },
  {
    "type": "]",
    "named": false
  },
  {
    "type": "and",
    "named": false
  },
  {
    "type": "false",
    "named": false
  },
  {
    "type": "gfp",
    "named": false
  },
  {
    "type": "lfp",
    "named": false
  },
  {
    "type": "not",
    "named": false
  },
  {
    "type": "or",
    "named": false
  },
  {
    "type": "state_set_variable",
    "named": true
  },
  {
    "type": "true",
    "named": false
  }
]